img_paradox/__init__.py
img_paradox/trans.py
img_paradox-0.0.1.dist-info/METADATA
img_paradox-0.0.1.dist-info/WHEEL
img_paradox-0.0.1.dist-info/top_level.txt
img_paradox-0.0.1.dist-info/RECORD
