Metadata-Version: 2.1
Name: img-paradox
Version: 0.0.1
Summary: A Tool for Scrambling and Unscrambling 
Author: 1uCif3R
Author-email: <ctfmail049@gmail.com>
Keywords: python,Image,Encryption,Scrambling
Classifier: Development Status :: 1 - Planning
Classifier: Intended Audience :: Developers
Classifier: Programming Language :: Python :: 3
Classifier: Operating System :: Unix
Classifier: Operating System :: MacOS :: MacOS X
Classifier: Operating System :: Microsoft :: Windows
Requires-Dist: numpy
Requires-Dist: pillow
